MANIFEST.in
README.rst
setup.py
LoreleiClient/Start.py
LoreleiClient/UI.py
LoreleiClient/__init__.py
LoreleiClient.egg-info/PKG-INFO
LoreleiClient.egg-info/SOURCES.txt
LoreleiClient.egg-info/dependency_links.txt
LoreleiClient.egg-info/not-zip-safe
LoreleiClient.egg-info/requires.txt
LoreleiClient.egg-info/top_level.txt
LoreleiClient/Images/Manager.py
LoreleiClient/Images/__init__.py
LoreleiClient/Images/Data/bracelet.png
LoreleiClient/Images/Data/chest_small.png
LoreleiClient/Images/Data/crest.png
LoreleiClient/Images/Data/feet_small.png
LoreleiClient/Images/Data/glove_small.png
LoreleiClient/Images/Data/helm_small.png
LoreleiClient/Images/Data/legs_small.png
LoreleiClient/Images/Data/necklace.png
LoreleiClient/Images/Data/ring_small.png
LoreleiClient/Images/Data/shield_small.png
LoreleiClient/Images/Data/sword_small.png
LoreleiClient/Settings/Screen.py
LoreleiClient/Settings/__init__.py
LoreleiClient/UIObjects/Input.py
LoreleiClient/UIObjects/__init__.py
LoreleiClient/Views/CharacterCreation.py
LoreleiClient/Views/Common.py
LoreleiClient/Views/Game.py
LoreleiClient/Views/Login.py
LoreleiClient/Views/__init__.py
LoreleiClient/Views/Modules/Attributes.py
LoreleiClient/Views/Modules/Chat.py
LoreleiClient/Views/Modules/Common.py
LoreleiClient/Views/Modules/Equipment.py
LoreleiClient/Views/Modules/Movement.py
LoreleiClient/Views/Modules/Room.py
LoreleiClient/Views/Modules/Statistics.py
LoreleiClient/Views/Modules/VitalBars.py
LoreleiClient/Views/Modules/__init__.py