Metadata-Version: 1.0
Name: LoreleiClient
Version: 0.1.8
Summary: The text based MUD made by Lorinthio
Home-page: https://pypi.org/project/LoreleiClient/
Author: Lorinthio
Author-email: benrandallswg@gmail.com
License: UNKNOWN
Platform: UNKNOWN
